chainweb/__init__.py
chainweb/chaindb.py
chainweb/header.py
chainweb/payload.py
chainweb/primitives.py
chainweb/utils.py
chainweb-0.0.1.dist-info/LICENSE
chainweb-0.0.1.dist-info/METADATA
chainweb-0.0.1.dist-info/WHEEL
chainweb-0.0.1.dist-info/top_level.txt
chainweb-0.0.1.dist-info/RECORD
