Metadata-Version: 2.1
Name: chainweb
Version: 0.0.1
Summary: Support for Chainweb in Python
Author-email: Lars Kuhtz <lars@kadena.io>
License: Copyright (c) 2024 Kadena LLC
Project-URL: Homepage, https://github.com/kadena-io/chainweb-py
Project-URL: Bug Tracker, https://github.com/kadena-io/chainweb-py/issues
Classifier: Programming Language :: Python :: 3
Classifier: License :: OSI Approved :: BSD License
Classifier: Operating System :: OS Independent
Requires-Python: >=3.12
License-File: LICENSE
Requires-Dist: rocksdb-py >=0.0.5
Requires-Dist: dictdiffer >=0.9.0
Requires-Dist: python-dotenv >=1.0.1
